karpyncho/pydantic_extensions/__init__.py
karpyncho_pydantic_extensions-0.3.5.dist-info/licenses/LICENSE
tests/__init__.py
tests/test_pydantic_extensions.py
karpyncho_pydantic_extensions-0.3.5.dist-info/METADATA
karpyncho_pydantic_extensions-0.3.5.dist-info/WHEEL
karpyncho_pydantic_extensions-0.3.5.dist-info/top_level.txt
karpyncho_pydantic_extensions-0.3.5.dist-info/RECORD
