Metadata-Version: 2.4
Name: karpyncho-pydantic-extensions
Version: 0.3.5
Summary: A collection of extensions and enhancements for the Pydantic library, providing custom mixins and utilities to enhance your data validation and serialization capabilities.
Author-email: Sebastian Quiles <qsebas@gmail.com>
Project-URL: homepage, https://github.com/karpyncho/pydantic-extensions
Project-URL: repository, https://github.com/karpyncho/pydantic-extensions
Project-URL: changelog, https://github.com/karpyncho/pydantic-extensions/blob/main/CHANGELOG.md
Classifier: Development Status :: 3 - Alpha
Classifier: License :: OSI Approved :: MIT License
Classifier: Natural Language :: English
Classifier: Operating System :: OS Independent
Classifier: Programming Language :: Python
Classifier: Programming Language :: Python :: 3.10
Classifier: Programming Language :: Python :: 3.11
Classifier: Programming Language :: Python :: 3.12
Classifier: Programming Language :: Python :: 3.13
Classifier: Programming Language :: Python :: 3.14
Requires-Python: >=3.10
License-File: LICENSE
Requires-Dist: pydantic>=2.0
Dynamic: license-file
